toolbox_pyspark/__init__.py
toolbox_pyspark/checks.py
toolbox_pyspark/cleaning.py
toolbox_pyspark/columns.py
toolbox_pyspark/constants.py
toolbox_pyspark/datetime.py
toolbox_pyspark/delta.py
toolbox_pyspark/dimensions.py
toolbox_pyspark/duplication.py
toolbox_pyspark/formatting.py
toolbox_pyspark/info.py
toolbox_pyspark/io.py
toolbox_pyspark/keys.py
toolbox_pyspark/scale.py
toolbox_pyspark/schema.py
toolbox_pyspark/types.py
toolbox_pyspark/utils/__init__.py
toolbox_pyspark/utils/exceptions.py
toolbox_pyspark/utils/warnings.py
toolbox_pyspark/utils/whitespaces.py
toolbox_pyspark-1.2.1.dist-info/LICENSE
toolbox_pyspark-1.2.1.dist-info/METADATA
toolbox_pyspark-1.2.1.dist-info/WHEEL
toolbox_pyspark-1.2.1.dist-info/RECORD
