Metadata-Version: 2.3
Name: toolbox-pyspark
Version: 1.2.1
Summary: Helper files/functions/classes for generic PySpark processes
License: MIT
Author: Admin
Author-email: toolbox-python@data-science-extensions.com
Maintainer: Admin
Maintainer-email: toolbox-python@data-science-extensions.com
Requires-Python: >3.9,<4.0
Classifier: Topic :: Software Development :: Build Tools
Classifier: Topic :: Software Development :: Libraries :: Python Modules
Classifier: Development Status :: 5 - Production/Stable
Classifier: License :: OSI Approved :: MIT License
Classifier: Programming Language :: Python :: 3
Classifier: Programming Language :: Python :: 3.10
Classifier: Programming Language :: Python :: 3.11
Classifier: Programming Language :: Python :: 3.12
Classifier: Programming Language :: Python :: 3.13
Classifier: Intended Audience :: Developers
Classifier: Topic :: Software Development :: Libraries :: Python Modules
Classifier: Topic :: Software Development :: Testing :: Unit
Classifier: Topic :: Utilities
Requires-Dist: delta-spark (==3.*)
Requires-Dist: numpy (==2.*)
Requires-Dist: pandas (==2.*)
Requires-Dist: pyspark (==3.*)
Requires-Dist: stamina (==24.*)
Requires-Dist: toolbox-python (==1.*)
Requires-Dist: typeguard (==4.*)
Project-URL: Changelog, https://github.com/data-science-extensions/toolbox-python/releases
Project-URL: Documentation, https://data-science-extensions.com/python-toolbox
Project-URL: Homepage, https://data-science-extensions.com/python-toolbox
Project-URL: Issues, https://github.com/data-science-extensions/toolbox-python/issues
Project-URL: Repository, https://github.com/data-science-extensions/toolbox-python
